AUTHORS
COPYING
MANIFEST.in
README
setup.cfg
setup.py
doc/Makefile
doc/appendix.rst
doc/examples.rst
doc/index.rst
doc/intro.rst
doc/make.bat
doc/usbtmc.rst
python_usbtmc.egg-info/PKG-INFO
python_usbtmc.egg-info/SOURCES.txt
python_usbtmc.egg-info/dependency_links.txt
python_usbtmc.egg-info/top_level.txt
usbtmc/__init__.py
usbtmc/usbtmc.py