Metadata-Version: 1.1
Name: python-usbtmc
Version: 0.1
Summary: Python USBTMC driver for controlling instruments over USB
Home-page: http://alexforencich.com/wiki/en/python-usbtmc/start
Author: Alex Forencich
Author-email: alex@alexforencich.com
License: MIT License
Download-URL: http://github.com/alexforencich/python-usbtmc/tarball/master
Keywords: USB USBTMC measurement instrument
Platform: UNKNOWN
Classifier: Development Status :: 4 - Beta
Classifier: Environment :: Console
Classifier: License :: OSI Approved :: MIT License
Classifier: Natural Language :: English
Classifier: Operating System :: OS Independent
Classifier: Intended Audience :: Science/Research
Classifier: Topic :: Scientific/Engineering :: Interface Engine/Protocol Translator
Classifier: Topic :: Software Development :: Libraries :: Python Modules
Classifier: Topic :: System :: Hardware :: Hardware Drivers
Classifier: Topic :: System :: Networking
Classifier: Programming Language :: Python :: 2
Classifier: Programming Language :: Python :: 3
